odoo/addons/voip_oca/README.rst
odoo/addons/voip_oca/__init__.py
odoo/addons/voip_oca/__manifest__.py
odoo/addons/voip_oca/data/neutralize.sql
odoo/addons/voip_oca/demo/demo_data.xml
odoo/addons/voip_oca/i18n/it.po
odoo/addons/voip_oca/i18n/voip_oca.pot
odoo/addons/voip_oca/models/__init__.py
odoo/addons/voip_oca/models/ir_http.py
odoo/addons/voip_oca/models/mail_activity.py
odoo/addons/voip_oca/models/mail_activity_mixin.py
odoo/addons/voip_oca/models/res_partner.py
odoo/addons/voip_oca/models/res_users.py
odoo/addons/voip_oca/models/voip_call.py
odoo/addons/voip_oca/models/voip_pbx.py
odoo/addons/voip_oca/readme/CONFIGURE.md
odoo/addons/voip_oca/readme/CONTEXT.md
odoo/addons/voip_oca/readme/CONTRIBUTORS.md
odoo/addons/voip_oca/readme/CREDITS.md
odoo/addons/voip_oca/readme/DESCRIPTION.md
odoo/addons/voip_oca/readme/ROADMAP.md
odoo/addons/voip_oca/readme/USAGE.md
odoo/addons/voip_oca/security/ir.model.access.csv
odoo/addons/voip_oca/static/audio/calltone.mp3
odoo/addons/voip_oca/static/audio/dialtone.mp3
odoo/addons/voip_oca/static/audio/ringbacktone.mp3
odoo/addons/voip_oca/static/description/actions.png
odoo/addons/voip_oca/static/description/activity_actions.png
odoo/addons/voip_oca/static/description/hidden_widget.png
odoo/addons/voip_oca/static/description/icon.png
odoo/addons/voip_oca/static/description/icon.svg
odoo/addons/voip_oca/static/description/index.html
odoo/addons/voip_oca/static/description/numpad.png
odoo/addons/voip_oca/static/description/partner.png
odoo/addons/voip_oca/static/description/received_call.png
odoo/addons/voip_oca/static/description/search.png
odoo/addons/voip_oca/static/description/softphone.png
odoo/addons/voip_oca/static/description/unknown_partner_actions.png
odoo/addons/voip_oca/static/description/widget.png
odoo/addons/voip_oca/static/lib/sip.js
odoo/addons/voip_oca/static/src/components/activity_list/activity_list.esm.js
odoo/addons/voip_oca/static/src/components/activity_list/activity_list.scss
odoo_addon_voip_oca-18.0.1.0.2.dist-info/METADATA
odoo_addon_voip_oca-18.0.1.0.2.dist-info/WHEEL
odoo_addon_voip_oca-18.0.1.0.2.dist-info/top_level.txt
odoo_addon_voip_oca-18.0.1.0.2.dist-info/RECORD
