Metadata-Version: 2.1
Name: odoo-addon-voip_oca
Version: 18.0.1.0.2
Requires-Python: >=3.10
Requires-Dist: odoo==18.0.*
Summary: Provides the use of Voip
Home-page: https://github.com/OCA/connector-telephony
License: AGPL-3
Author: Dixmit, Odoo Community Association (OCA)
Author-email: support@odoo-community.org
Classifier: Programming Language :: Python
Classifier: Framework :: Odoo
Classifier: Framework :: Odoo :: 18.0
Classifier: License :: OSI Approved :: GNU Affero General Public License v3
